{
  "name": "Derrick Hammond",
  "age": 47,
  "address": {
    "street": "Fuih Parkway",
    "city": "Vevagola",
    "state": "CO",
    "zip": "58542"
  },
  "contact": {
    "phone": "(645) 862-7997",
    "servicePhone": "800248672"
  },
  "birthday": "1963-01-15T14:34:14.882Z",
  "ip": "113.81.181.152",
  "foo": "bar",
  "profile": {
    "about": "Punib dika nen huwjij wi igievjac zos ok tehenmo zuutzap nanoj hefsirere saz ri cu om mujiw. Nazep buh zu zifa goguvmu jic ru luviv pahuz wupujo fajpipu liwnovo vuc vi kezod poh. Ebhek judfigal bomol dozwes cupaati hipwupas caje wohevduc wigwepe perguw jimboheva pof monhi pofa lilurir. Labmu inno megwi va gaj javsoghal baddo el nofhibwiz kiz taeso vesivder kikat hasevevim kimom hi uromoc. Zuzat tacdo obe wavoduv bu jir aftovvad has vudiju vig molpo wad wic. Cuf gifali cif cahic hacvusvo uju effepib ev wedpeber wo ip ajipunmo evarim citcili ekakbej so ic. Vus zi ewijaogu topdeb zuhid abadiej cugfus vajcifi dirahaj buj pedof miv gojle jow fodicod pokimaj luvpaglo ottareb.",
    "bio": "Gutvu patopa zogakpu fevsuwad kumosuzuv ha uwza siszuuzo rafrokano mumup ajhin ci. Voz gobwu hezorilu mijobul gonsag ha bob woktu siima puzwar gathumu cigo cuh muspuaw zusir hupenwi. Wutadowi enohirsi ic bub jineer nulo tih ernalki wal ga uho siv be zuta va te va ce. Gal vomnes vo za kibcuon vewjuk ja newgojo hubivazek hipwa huigbeb pek iva re renvi wu ukwev jasupug. Ad jiclatu cebe riviplos rejosize movu cu guve purim ali hezadjuj joren. So zenfubasa puvlefe mutur um soh nanono er eto becog de eslur powawpe duvlevnij jis."
  },
  "apiKey": "8816a9543b0a4456e21f91c26f3c920ee7f786b3de33febe16fdfff3af856e2c",
  "currency": {
    "code": "BWP",
    "name": "Botswana Pula"
  }
}