{
  "name": "Celia Vargas",
  "age": 48,
  "address": {
    "street": "Azazo Pass",
    "city": "Loipivo",
    "state": "RI",
    "zip": "72737"
  },
  "contact": {
    "phone": "(269) 382-8105",
    "servicePhone": "800998311"
  },
  "birthday": "2005-08-07T14:00:26.481Z",
  "ip": "15.250.30.119",
  "foo": "bar",
  "profile": {
    "about": "Titid gafpi tubot obsovfu ahoni hucmiho siv ifoget refa ceav gapmu dadhe sa uk waj. Rakseh po tosbu epi ote viehoku ifaci ic kujiwaw igdegig gej dih. Zumsa wibuw li gon tanegler itulemgat oge negnik oco subulaz kawkalwo sobgeboj itijun ud jin ektubkal emsat.",
    "bio": "Fouwkid resa fondedhi funjurem pu fenar idi wop wi asiri ut acan vobav rouzgop. Uzoac fi isbimibe ewlar ca leabawe alomog karudag votil paaf kibro igeef. Vodobe zajece bazgah moz vizakzul jur behubi ji rem apko awi vepid etisooj rin pades. Tis ebinemmo jo zipelen wek tut bokroze nun roh iromihfuv volubu taba girwo zoruzale bauc eg. Ej kewatguf lowotnek nalud tu ubilatig vabof idzi cos zigdutge jidor ku ikamim rafoz fa ev vopacuemi."
  },
  "apiKey": "04e40acc8985b158b9aa1a2398f0cae2b016d924492a223274ba1ccc621cf667",
  "currency": {
    "code": "AUD",
    "name": "Australia Dollar"
  }
}