{
  "name": "Mattie Martinez",
  "age": 54,
  "address": {
    "street": "Kezad Avenue",
    "city": "Aflumlo",
    "state": "AL",
    "zip": "09782"
  },
  "contact": {
    "phone": "(354) 334-4436",
    "servicePhone": "800463632"
  },
  "birthday": "1962-12-30T19:54:00.556Z",
  "ip": "234.229.196.135",
  "foo": "bar",
  "profile": {
    "about": "Dito hadce nez abo kades li fanec dece hid wuv enabezi bibi muag mekun lited ducub. Totuj row loif te tudat utijudpa bocedco vagheru jew avoseuh ucli kugem. Ujava fog lek oguetgep ziji tivfap waebwuh bidci ju hovsiib wab ebafaes feprofmu ubnub imoju ilkew culorbos. Cajonu tenalar utu zakzalih mon taaloruh ew jahobne hize bujjabo kus pu min zusmahi hos diju jihpecjo fecpo.",
    "bio": "Nidvet atpus bujab jad apa gad du nogulki zad ozhafsa petivik wejamfa towun isiine wopi. Iffam natjah kom rizri regogoc luz tuwzodi wub sa gud couc dowebis ci wokluf lotcun consezrup zuhfe duwusam. Atumukdo levrewop fijzul vu leila hizosja sij zedesisu muzuccu sovuhbo zabid pihamecik jeukica zafufi. Aka net sam efouh jur eduip vicfu jajopci cebalcab ufijlod wakse ob juz felifi rofgaob urfopvo ne. Calizo noliv vahzu tibfowa tefwiw gevezoc fi ulrut sezilsa of bitfeapi on wicte tijiduv heeca baspep puku lewob. Gu pirsigag cavisra ezu urkokwe gifne wiw if kojjaba sose tij waola niuma."
  },
  "apiKey": "efae230437b1d02af6d72e5315057503746ea13b3a058cbb11cea034403f810a",
  "currency": {
    "code": "KMF",
    "name": "Comoros Franc"
  }
}